movienight/_MovieFinder.py
movienight/__init__.py
movienight/datasets/__init__.py
movienight/datasets/_base.py
movienight/datasets/_config.py
movienight/datasets/_tmdb.py
movienight/datasets/data/tmdb.csv
movienight-0.1.2.dist-info/WHEEL
movienight-0.1.2.dist-info/METADATA
movienight-0.1.2.dist-info/RECORD
